{
    "BT3ADaXAw8k": {
        "lat": 41.4879181865, 
        "lon": -120.5427479462
    }, 
    "BT672gBgW1u": {
        "lat": 41.5292, 
        "lon": -120.173
    }, 
    "BUFFmhkgkoB": {
        "lat": 41.9466666667, 
        "lon": -121.565
    }, 
    "BUXaX-rg3BV": {
        "lat": 40.6782, 
        "lon": -122.37
    }, 
    "BTzcy8yAd78": {
        "lat": 38.4052, 
        "lon": -122.851
    }, 
    "BTxuamIAFep": {
        "lat": 38.2375, 
        "lon": -122.962
    }, 
    "BT13cOGg4sR": {
        "lat": 41.0188888889, 
        "lon": -121.6513888889
    }, 
    "BUa7A3NAOp8": {
        "lat": 40.8387659, 
        "lon": -122.0283326
    }, 
    "BUBE9viA6g4": {
        "lat": 41.5036, 
        "lon": -120.944
    }, 
    "BT5nPqqglid": {
        "lat": 41.5330038157, 
        "lon": -120.0784898007
    }, 
    "BUCVzyMg20S": {
        "lat": 41.7090925621, 
        "lon": -121.5131664276
    }, 
    "BTwUN5FAfp1": {
        "lat": 37.4542, 
        "lon": -122.179
    }
}